openmesh.cpython-39-darwin.so
openmesh-1.2.1.dist-info/LICENSE
openmesh-1.2.1.dist-info/METADATA
openmesh-1.2.1.dist-info/WHEEL
openmesh-1.2.1.dist-info/top_level.txt
openmesh-1.2.1.dist-info/RECORD
