Metadata-Version: 2.1
Name: openmesh
Version: 1.2.1
Summary: a versatile halfedge-based data structure for representing and manipulating polygon meshes
Home-page: https://gitlab.vci.rwth-aachen.de:9000/OpenMesh/openmesh-python
Author: Alexander Dielen, Isaak Lim, Janis Born
Author-email: vci-pypi@cs.rwth-aachen.de
License: BSD 3-Clause
Project-URL: Source, https://gitlab.vci.rwth-aachen.de:9000/OpenMesh/openmesh-python
Project-URL: Tracker, https://gitlab.vci.rwth-aachen.de:9000/OpenMesh/openmesh-python/issues
Platform: UNKNOWN
Classifier: Development Status :: 4 - Beta
Classifier: Programming Language :: Python :: 3.9
Classifier: Topic :: Multimedia :: Graphics
